Bb_rest_helper.py
Bb_rest_helper-2.0.1.dist-info/LICENSE.md
Bb_rest_helper-2.0.1.dist-info/METADATA
Bb_rest_helper-2.0.1.dist-info/WHEEL
Bb_rest_helper-2.0.1.dist-info/top_level.txt
Bb_rest_helper-2.0.1.dist-info/RECORD
