Metadata-Version: 2.1
Name: Bb-rest-helper
Version: 2.0.1
Summary: A Python 3 library to simplify working with Blackboard APIs.
Home-page: https://github.com/JgregoriBb/Bb_rest_helper
Author: Javier Gregori
Author-email: javier.gregori@blackboard.com
License: UNKNOWN
Platform: UNKNOWN
Classifier: Programming Language :: Python :: 3
Classifier: License :: Other/Proprietary License
Classifier: Operating System :: OS Independent
Requires-Python: >=3.7
License-File: LICENSE.md
Requires-Dist: PyJWT (>=2.3.0)
Requires-Dist: requests (>=2.24.0)
